minestudio/__init__.py
minestudio/benchmark/__init__.py
minestudio/benchmark/test.py
minestudio/benchmark/test_pipeline.py
minestudio/benchmark/auto_eval/README.md
minestudio/benchmark/auto_eval/batch_video_rating.py
minestudio/benchmark/auto_eval/individual_video_rating.py
minestudio/benchmark/auto_eval/video_comparison.py
minestudio/benchmark/auto_eval/criteria_files/build_a_waterfall.txt
minestudio/benchmark/auto_eval/criteria_files/build_dig3fill1.txt
minestudio/benchmark/auto_eval/criteria_files/build_gate.txt
minestudio/benchmark/auto_eval/criteria_files/build_golems.txt
minestudio/benchmark/auto_eval/criteria_files/build_nether_portal.txt
minestudio/benchmark/auto_eval/criteria_files/build_obsidian.txt
minestudio/benchmark/auto_eval/criteria_files/build_pillar.txt
minestudio/benchmark/auto_eval/criteria_files/build_snow_golem.txt
minestudio/benchmark/auto_eval/criteria_files/build_snow_golems.txt
minestudio/benchmark/auto_eval/criteria_files/build_waterfall.txt
minestudio/benchmark/auto_eval/criteria_files/carve_pumpkin.txt
minestudio/benchmark/auto_eval/criteria_files/carve_pumpkins.txt
minestudio/benchmark/auto_eval/criteria_files/clean_up.txt
minestudio/benchmark/auto_eval/criteria_files/climb_the_mountain.txt
minestudio/benchmark/auto_eval/criteria_files/collect_dirt.txt
minestudio/benchmark/auto_eval/criteria_files/collect_grass.txt
minestudio/benchmark/auto_eval/criteria_files/collect_seagrass.txt
minestudio/benchmark/auto_eval/criteria_files/collect_wood.txt
minestudio/benchmark/auto_eval/criteria_files/collect_wool.txt
minestudio/benchmark/auto_eval/criteria_files/combat_enderman.txt
minestudio/benchmark/auto_eval/criteria_files/combat_enemies.txt
minestudio/benchmark/auto_eval/criteria_files/combat_skeletons.txt
minestudio/benchmark/auto_eval/criteria_files/combat_spider.txt
minestudio/benchmark/auto_eval/criteria_files/combat_spiders.txt
minestudio/benchmark/auto_eval/criteria_files/combat_zombies.txt
minestudio-1.1.6.dist-info/licenses/LICENSE
minestudio-1.1.6.dist-info/METADATA
minestudio-1.1.6.dist-info/WHEEL
minestudio-1.1.6.dist-info/top_level.txt
minestudio-1.1.6.dist-info/RECORD
