Metadata-Version: 2.4
Name: minestudio
Version: 1.1.6
Summary: A simple and efficient Minecraft Agent development kit for AI research.
Author-email: CraftJarvis <craftjarvis@outlook.com>
Requires-Python: >=3.10
License-File: LICENSE
Requires-Dist: av==13.1.0
Requires-Dist: opencv-python==4.8.0.74
Requires-Dist: opencv-python-headless==4.8.0.74
Requires-Dist: setuptools
Requires-Dist: tqdm
Requires-Dist: numpy
Requires-Dist: requests
Requires-Dist: ipython
Requires-Dist: typing
Requires-Dist: gym
Requires-Dist: gym3
Requires-Dist: gymnasium
Requires-Dist: hydra_colorlog
Requires-Dist: hydra-core>=1.3.2
Requires-Dist: lmdb
Requires-Dist: wandb
Requires-Dist: torch>=2.3.1
Requires-Dist: lightning
Requires-Dist: scipy
Requires-Dist: rich
Requires-Dist: coloredlogs
Requires-Dist: daemoniker
Requires-Dist: lxml
Requires-Dist: cuda-python; platform_system != "Darwin"
Requires-Dist: diskcache
Requires-Dist: albumentations
Requires-Dist: einops
Requires-Dist: timm
Requires-Dist: transformers
Requires-Dist: Pyro4
Requires-Dist: xmltodict
Requires-Dist: pyrender==0.1.25
Requires-Dist: pyglet
Requires-Dist: imgui
Requires-Dist: pyopengl
Requires-Dist: ray
Requires-Dist: minecraft_data==3.20.0
Requires-Dist: absl-py
Requires-Dist: dm-tree
Requires-Dist: x_transformers==0.27.1
Dynamic: license-file
